hebikani/__init__.py
hebikani/graph.py
hebikani/hebikani.py
hebikani/input.py
hebikani/settings.py
hebikani/typing.py
hebikani-1.8.1.dist-info/LICENSE
hebikani-1.8.1.dist-info/METADATA
hebikani-1.8.1.dist-info/WHEEL
hebikani-1.8.1.dist-info/entry_points.txt
hebikani-1.8.1.dist-info/RECORD
