Metadata-Version: 2.1
Name: hebikani
Version: 1.8.1
Summary: WaniKani command line interface
Home-page: https://github.com/ajite/hebikani
License: MIT
Author: Augustin
Author-email: ajitekun@gmail.com
Requires-Python: >=3.9,<4.0
Classifier: License :: OSI Approved :: MIT License
Classifier: Programming Language :: Python :: 3
Classifier: Programming Language :: Python :: 3.9
Classifier: Programming Language :: Python :: 3.10
Classifier: Programming Language :: Python :: 3.11
Classifier: Programming Language :: Python :: 3.12
Requires-Dist: Pillow (>=9.1.0,<10.0.0)
Requires-Dist: PyGObject (>=3.42.1,<4.0.0) ; sys_platform == "linux"
Requires-Dist: ascii-magic (>=1.6,<2.0)
Requires-Dist: cairosvg (>=2.7.1,<3.0.0)
Requires-Dist: colorama (>=0.4.4,<0.5.0)
Requires-Dist: halo (>=0.0.31,<0.0.32)
Requires-Dist: mutagen (>=1.45.1,<2.0.0) ; sys_platform == "win32"
Requires-Dist: playsound (==1.2.2)
Requires-Dist: pyobjc (>=8.5,<10.0) ; sys_platform == "darwin"
Requires-Dist: python-romkan-ng (>=0.3.0,<0.4.0)
Requires-Dist: requests (>=2.27.1,<3.0.0)
Project-URL: Repository, https://github.com/ajite/hebikani
